boj/__init__.py
boj/user.py
boj_tool-1.1.4.dist-info/LICENSE
boj_tool-1.1.4.dist-info/METADATA
boj_tool-1.1.4.dist-info/WHEEL
boj_tool-1.1.4.dist-info/entry_points.txt
boj_tool-1.1.4.dist-info/top_level.txt
boj_tool-1.1.4.dist-info/RECORD
