Metadata-Version: 2.1
Name: boj-tool
Version: 1.1.4
Summary: A tool for submitting to BOJ
Home-page: UNKNOWN
Author: Ryang Sohn
Author-email: loop.infinitely@gmail.com
License: UNKNOWN
Project-URL: Bug Reports, https://github.com/sohnryang/boj-tool/issues
Project-URL: Source, https://github.com/sohnryang/boj-tool
Platform: UNKNOWN
Requires-Dist: colorama
Requires-Dist: requests
Requires-Dist: bs4
Requires-Dist: xdg (==3.0.2)
